target_s3_avro/__init__.py
target_s3_avro-1.2.dist-info/LICENSE
target_s3_avro-1.2.dist-info/METADATA
target_s3_avro-1.2.dist-info/WHEEL
target_s3_avro-1.2.dist-info/entry_points.txt
target_s3_avro-1.2.dist-info/top_level.txt
target_s3_avro-1.2.dist-info/RECORD
