Metadata-Version: 2.1
Name: target-s3-avro
Version: 1.2
Summary: Singer.io target for extracting data into s3 stored as AVRO
Home-page: https://github.com/faumel/target-s3-avro
Author: Froilan A. Umel
Author-email: froilan.umel@gmail.com
License: UNKNOWN
Platform: UNKNOWN
Classifier: Programming Language :: Python :: 3 :: Only
Requires-Dist: singer-python (>=5.0.12)
Requires-Dist: boto3 (>=1.4.1)
Requires-Dist: avro-python3 (>=1.9.0)
